{
  "$schema": "https://jsr.io/schema/config-file.v1.json",
  "name": "@omochice/redmine",
  "version": "2.0.0",
  "exports": {
    ".": "./result/mod.ts",
    "./result": "./result/mod.ts",
    "./result/projects": "./result/projects/mod.ts",
    "./result/projects/archive": "./result/projects/archive.ts",
    "./result/projects/create": "./result/projects/create.ts",
    "./result/projects/list": "./result/projects/list.ts",
    "./result/projects/show": "./result/projects/show.ts",
    "./result/projects/update": "./result/projects/update.ts",
    "./result/projects/delete": "./result/projects/delete.ts",
    "./result/trackers": "./result/trackers/mod.ts",
    "./result/trackers/list": "./result/trackers/list.ts",
    "./result/issue-templates": "./result/issue-templates/mod.ts",
    "./result/issue-templates/list": "./result/issue-templates/list.ts",
    "./result/wiki-pages": "./result/wiki-pages/mod.ts",
    "./result/wiki-pages/create": "./result/wiki-pages/create.ts",
    "./result/wiki-pages/list": "./result/wiki-pages/list.ts",
    "./result/wiki-pages/show": "./result/wiki-pages/show.ts",
    "./result/wiki-pages/update": "./result/wiki-pages/update.ts",
    "./result/wiki-pages/delete": "./result/wiki-pages/delete.ts",
    "./result/issues": "./result/issues/mod.ts",
    "./result/issues/create": "./result/issues/create.ts",
    "./result/issues/list": "./result/issues/list.ts",
    "./result/issues/show": "./result/issues/show.ts",
    "./result/issues/update": "./result/issues/update.ts",
    "./throwable": "./throwable/mod.ts",
    "./throwable/projects": "./throwable/projects/mod.ts",
    "./throwable/projects/archive": "./throwable/projects/archive.ts",
    "./throwable/projects/type": "./throwable/projects/type.ts",
    "./throwable/projects/create": "./throwable/projects/create.ts",
    "./throwable/projects/list": "./throwable/projects/list.ts",
    "./throwable/projects/show": "./throwable/projects/show.ts",
    "./throwable/projects/update": "./throwable/projects/update.ts",
    "./throwable/projects/validator": "./throwable/projects/validator.ts",
    "./throwable/projects/delete": "./throwable/projects/delete.ts",
    "./throwable/trackers": "./throwable/trackers/mod.ts",
    "./throwable/trackers/type": "./throwable/trackers/type.ts",
    "./throwable/trackers/list": "./throwable/trackers/list.ts",
    "./throwable/trackers/validator": "./throwable/trackers/validator.ts",
    "./throwable/issue-templates": "./throwable/issue-templates/mod.ts",
    "./throwable/issue-templates/type": "./throwable/issue-templates/type.ts",
    "./throwable/issue-templates/list": "./throwable/issue-templates/list.ts",
    "./throwable/issue-templates/validator": "./throwable/issue-templates/validator.ts",
    "./throwable/wiki-pages": "./throwable/wiki-pages/mod.ts",
    "./throwable/wiki-pages/type": "./throwable/wiki-pages/type.ts",
    "./throwable/wiki-pages/create": "./throwable/wiki-pages/create.ts",
    "./throwable/wiki-pages/list": "./throwable/wiki-pages/list.ts",
    "./throwable/wiki-pages/show": "./throwable/wiki-pages/show.ts",
    "./throwable/wiki-pages/update": "./throwable/wiki-pages/update.ts",
    "./throwable/wiki-pages/validator": "./throwable/wiki-pages/validator.ts",
    "./throwable/wiki-pages/delete": "./throwable/wiki-pages/delete.ts",
    "./throwable/issues": "./throwable/issues/mod.ts",
    "./throwable/issues/type": "./throwable/issues/type.ts",
    "./throwable/issues/create": "./throwable/issues/create.ts",
    "./throwable/issues/list": "./throwable/issues/list.ts",
    "./throwable/issues/show": "./throwable/issues/show.ts",
    "./throwable/issues/update": "./throwable/issues/update.ts",
    "./throwable/issues/validator": "./throwable/issues/validator.ts"
  },
  "publish": {
    "include": [
      "README.md",
      "LICENSE",
      "./**/*.ts"
    ],
    "exclude": [
      "./**/*.test.ts",
      "./**/_mock.ts"
    ]
  }
}
